{"playerList":[{"playerId":"1","name":"shubham","countriesOwned":["25","40","23","9","33","14","1","11","39","21","18","22","34","15"],"continentOwned":[],"totalArmiesOwned":39,"reinforcementArmies":0,"currentPhase":"attack","exchangeCards":0,"cards":[]},{"playerId":"2","name":"devdutt","countriesOwned":["29","7","37","16","31","8","35","17","24","42","5","41","13","30"],"continentOwned":[],"totalArmiesOwned":35,"reinforcementArmies":0,"currentPhase":null,"exchangeCards":0,"cards":[]},{"playerId":"3","name":"dhaval","countriesOwned":["20","36","12","32","27","38","2","3","28","19","4","10","26","6"],"continentOwned":[],"totalArmiesOwned":35,"reinforcementArmies":0,"currentPhase":null,"exchangeCards":0,"cards":[]}],"currentPlayer":{"playerId":"1","name":"shubham","countriesOwned":["25","40","23","9","33","14","1","11","39","21","18","22","34","15"],"continentOwned":[],"totalArmiesOwned":39,"reinforcementArmies":0,"currentPhase":"attack","exchangeCards":0,"cards":[]},"attackerDiceValues":null,"defenderDiceValues":null,"attackingCountry":null,"defendingCountry":null}